{
  "attempts": [
    {
      "error": "GET https://api.binance.com/api/v3/klines?symbol=BTCUSDT&interval=1m&limit=200 failed: HTTP Error 451: ",
      "fetched_at": "2026-06-29T23:16:06Z",
      "kind": "candles_1m",
      "latency_ms": 183,
      "notes": [],
      "source": "binance",
      "status": "failed"
    },
    {
      "error": null,
      "fetched_at": "2026-06-29T23:16:06Z",
      "kind": "candles_1m",
      "latency_ms": 30,
      "notes": [],
      "source": "coinbase",
      "status": "ok"
    }
  ],
  "data": {
    "candles": [
      {
        "close": 60393.97,
        "close_time_ms": 1782762960000,
        "high": 60435.9,
        "low": 60371.03,
        "open": 60373.21,
        "open_time_ms": 1782762900000,
        "volume": 24.57179096
      },
      {
        "close": 60323.59,
        "close_time_ms": 1782763020000,
        "high": 60393.96,
        "low": 60316.89,
        "open": 60393.96,
        "open_time_ms": 1782762960000,
        "volume": 8.249937
      },
      {
        "close": 60369.43,
        "close_time_ms": 1782763080000,
        "high": 60372.42,
        "low": 60321.25,
        "open": 60323.38,
        "open_time_ms": 1782763020000,
        "volume": 10.54003942
      },
      {
        "close": 60357.97,
        "close_time_ms": 1782763140000,
        "high": 60372.43,
        "low": 60341.98,
        "open": 60369.08,
        "open_time_ms": 1782763080000,
        "volume": 9.87244434
      },
      {
        "close": 60332.0,
        "close_time_ms": 1782763200000,
        "high": 60366.0,
        "low": 60323.01,
        "open": 60357.96,
        "open_time_ms": 1782763140000,
        "volume": 12.75893182
      },
      {
        "close": 60362.12,
        "close_time_ms": 1782763260000,
        "high": 60375.83,
        "low": 60324.0,
        "open": 60327.87,
        "open_time_ms": 1782763200000,
        "volume": 11.64884556
      },
      {
        "close": 60387.0,
        "close_time_ms": 1782763320000,
        "high": 60404.27,
        "low": 60362.12,
        "open": 60362.12,
        "open_time_ms": 1782763260000,
        "volume": 5.37695096
      },
      {
        "close": 60444.12,
        "close_time_ms": 1782763380000,
        "high": 60450.05,
        "low": 60385.76,
        "open": 60385.76,
        "open_time_ms": 1782763320000,
        "volume": 7.07229285
      },
      {
        "close": 60435.18,
        "close_time_ms": 1782763440000,
        "high": 60453.71,
        "low": 60409.06,
        "open": 60444.11,
        "open_time_ms": 1782763380000,
        "volume": 4.75327809
      },
      {
        "close": 60409.52,
        "close_time_ms": 1782763500000,
        "high": 60435.18,
        "low": 60393.97,
        "open": 60435.18,
        "open_time_ms": 1782763440000,
        "volume": 6.1837716
      },
      {
        "close": 60391.7,
        "close_time_ms": 1782763560000,
        "high": 60414.73,
        "low": 60375.09,
        "open": 60409.53,
        "open_time_ms": 1782763500000,
        "volume": 10.5201533
      },
      {
        "close": 60399.05,
        "close_time_ms": 1782763620000,
        "high": 60406.41,
        "low": 60365.59,
        "open": 60393.59,
        "open_time_ms": 1782763560000,
        "volume": 8.03802801
      },
      {
        "close": 60356.86,
        "close_time_ms": 1782763680000,
        "high": 60403.01,
        "low": 60336.72,
        "open": 60399.04,
        "open_time_ms": 1782763620000,
        "volume": 6.52689176
      },
      {
        "close": 60362.19,
        "close_time_ms": 1782763740000,
        "high": 60379.79,
        "low": 60356.96,
        "open": 60356.96,
        "open_time_ms": 1782763680000,
        "volume": 7.81443959
      },
      {
        "close": 60354.7,
        "close_time_ms": 1782763800000,
        "high": 60392.0,
        "low": 60354.7,
        "open": 60362.9,
        "open_time_ms": 1782763740000,
        "volume": 8.26452997
      },
      {
        "close": 60363.76,
        "close_time_ms": 1782763860000,
        "high": 60390.94,
        "low": 60353.0,
        "open": 60354.7,
        "open_time_ms": 1782763800000,
        "volume": 10.6466824
      },
      {
        "close": 60344.08,
        "close_time_ms": 1782763920000,
        "high": 60375.03,
        "low": 60326.93,
        "open": 60363.93,
        "open_time_ms": 1782763860000,
        "volume": 5.9693631
      },
      {
        "close": 60390.14,
        "close_time_ms": 1782763980000,
        "high": 60391.64,
        "low": 60340.2,
        "open": 60344.07,
        "open_time_ms": 1782763920000,
        "volume": 6.2930494
      },
      {
        "close": 60336.62,
        "close_time_ms": 1782764040000,
        "high": 60390.25,
        "low": 60336.62,
        "open": 60390.13,
        "open_time_ms": 1782763980000,
        "volume": 2.89842588
      },
      {
        "close": 60333.82,
        "close_time_ms": 1782764100000,
        "high": 60348.66,
        "low": 60327.68,
        "open": 60338.28,
        "open_time_ms": 1782764040000,
        "volume": 2.02434533
      },
      {
        "close": 60309.39,
        "close_time_ms": 1782764160000,
        "high": 60344.0,
        "low": 60307.36,
        "open": 60333.81,
        "open_time_ms": 1782764100000,
        "volume": 3.12601834
      },
      {
        "close": 60313.26,
        "close_time_ms": 1782764220000,
        "high": 60331.34,
        "low": 60300.81,
        "open": 60306.38,
        "open_time_ms": 1782764160000,
        "volume": 4.16223319
      },
      {
        "close": 60312.74,
        "close_time_ms": 1782764280000,
        "high": 60330.12,
        "low": 60306.38,
        "open": 60313.26,
        "open_time_ms": 1782764220000,
        "volume": 3.74352732
      },
      {
        "close": 60265.24,
        "close_time_ms": 1782764340000,
        "high": 60312.73,
        "low": 60261.08,
        "open": 60312.73,
        "open_time_ms": 1782764280000,
        "volume": 6.20430388
      },
      {
        "close": 60282.0,
        "close_time_ms": 1782764400000,
        "high": 60282.0,
        "low": 60259.32,
        "open": 60262.63,
        "open_time_ms": 1782764340000,
        "volume": 2.65640915
      },
      {
        "close": 60300.46,
        "close_time_ms": 1782764460000,
        "high": 60309.33,
        "low": 60281.06,
        "open": 60281.99,
        "open_time_ms": 1782764400000,
        "volume": 2.04615186
      },
      {
        "close": 60301.83,
        "close_time_ms": 1782764520000,
        "high": 60301.83,
        "low": 60279.26,
        "open": 60300.46,
        "open_time_ms": 1782764460000,
        "volume": 11.06996555
      },
      {
        "close": 60335.47,
        "close_time_ms": 1782764580000,
        "high": 60335.84,
        "low": 60300.01,
        "open": 60301.82,
        "open_time_ms": 1782764520000,
        "volume": 4.97916899
      },
      {
        "close": 60338.76,
        "close_time_ms": 1782764640000,
        "high": 60345.64,
        "low": 60329.2,
        "open": 60335.47,
        "open_time_ms": 1782764580000,
        "volume": 2.66102672
      },
      {
        "close": 60330.97,
        "close_time_ms": 1782764700000,
        "high": 60356.26,
        "low": 60329.04,
        "open": 60339.99,
        "open_time_ms": 1782764640000,
        "volume": 3.22665322
      },
      {
        "close": 60351.78,
        "close_time_ms": 1782764760000,
        "high": 60351.99,
        "low": 60327.54,
        "open": 60330.55,
        "open_time_ms": 1782764700000,
        "volume": 1.7538366
      },
      {
        "close": 60340.95,
        "close_time_ms": 1782764820000,
        "high": 60393.02,
        "low": 60284.0,
        "open": 60351.78,
        "open_time_ms": 1782764760000,
        "volume": 7.31102183
      },
      {
        "close": 60331.54,
        "close_time_ms": 1782764880000,
        "high": 60341.68,
        "low": 60299.0,
        "open": 60340.95,
        "open_time_ms": 1782764820000,
        "volume": 5.6156243
      },
      {
        "close": 60316.43,
        "close_time_ms": 1782764940000,
        "high": 60332.11,
        "low": 60313.54,
        "open": 60331.54,
        "open_time_ms": 1782764880000,
        "volume": 1.91565311
      },
      {
        "close": 60311.52,
        "close_time_ms": 1782765000000,
        "high": 60316.43,
        "low": 60300.0,
        "open": 60316.43,
        "open_time_ms": 1782764940000,
        "volume": 3.77832853
      },
      {
        "close": 60316.0,
        "close_time_ms": 1782765060000,
        "high": 60340.0,
        "low": 60311.51,
        "open": 60311.51,
        "open_time_ms": 1782765000000,
        "volume": 2.98825039
      },
      {
        "close": 60309.25,
        "close_time_ms": 1782765120000,
        "high": 60318.0,
        "low": 60304.0,
        "open": 60315.71,
        "open_time_ms": 1782765060000,
        "volume": 1.51982642
      },
      {
        "close": 60337.13,
        "close_time_ms": 1782765180000,
        "high": 60337.15,
        "low": 60309.25,
        "open": 60309.25,
        "open_time_ms": 1782765120000,
        "volume": 1.63323907
      },
      {
        "close": 60345.5,
        "close_time_ms": 1782765240000,
        "high": 60347.46,
        "low": 60326.01,
        "open": 60337.13,
        "open_time_ms": 1782765180000,
        "volume": 1.08377357
      },
      {
        "close": 60374.27,
        "close_time_ms": 1782765300000,
        "high": 60379.5,
        "low": 60345.5,
        "open": 60345.51,
        "open_time_ms": 1782765240000,
        "volume": 2.93431542
      },
      {
        "close": 60367.79,
        "close_time_ms": 1782765360000,
        "high": 60378.86,
        "low": 60362.01,
        "open": 60374.28,
        "open_time_ms": 1782765300000,
        "volume": 1.33392174
      },
      {
        "close": 60367.71,
        "close_time_ms": 1782765420000,
        "high": 60380.0,
        "low": 60360.0,
        "open": 60367.78,
        "open_time_ms": 1782765360000,
        "volume": 3.24532271
      },
      {
        "close": 60333.61,
        "close_time_ms": 1782765480000,
        "high": 60367.72,
        "low": 60321.48,
        "open": 60367.71,
        "open_time_ms": 1782765420000,
        "volume": 1.66065441
      },
      {
        "close": 60349.58,
        "close_time_ms": 1782765540000,
        "high": 60360.02,
        "low": 60332.21,
        "open": 60333.61,
        "open_time_ms": 1782765480000,
        "volume": 2.88899622
      },
      {
        "close": 60369.73,
        "close_time_ms": 1782765600000,
        "high": 60384.29,
        "low": 60329.99,
        "open": 60349.57,
        "open_time_ms": 1782765540000,
        "volume": 14.51342654
      },
      {
        "close": 60348.3,
        "close_time_ms": 1782765660000,
        "high": 60369.72,
        "low": 60329.66,
        "open": 60369.72,
        "open_time_ms": 1782765600000,
        "volume": 6.01271865
      },
      {
        "close": 60352.04,
        "close_time_ms": 1782765720000,
        "high": 60366.48,
        "low": 60344.23,
        "open": 60348.31,
        "open_time_ms": 1782765660000,
        "volume": 7.95608891
      },
      {
        "close": 60339.63,
        "close_time_ms": 1782765780000,
        "high": 60352.04,
        "low": 60339.63,
        "open": 60352.03,
        "open_time_ms": 1782765720000,
        "volume": 1.88334211
      },
      {
        "close": 60330.85,
        "close_time_ms": 1782765840000,
        "high": 60358.59,
        "low": 60330.85,
        "open": 60339.64,
        "open_time_ms": 1782765780000,
        "volume": 3.59144844
      },
      {
        "close": 60322.39,
        "close_time_ms": 1782765900000,
        "high": 60330.86,
        "low": 60303.85,
        "open": 60330.85,
        "open_time_ms": 1782765840000,
        "volume": 3.62384532
      },
      {
        "close": 60259.78,
        "close_time_ms": 1782765960000,
        "high": 60322.39,
        "low": 60252.0,
        "open": 60322.39,
        "open_time_ms": 1782765900000,
        "volume": 10.51072637
      },
      {
        "close": 60282.2,
        "close_time_ms": 1782766020000,
        "high": 60293.97,
        "low": 60259.77,
        "open": 60259.77,
        "open_time_ms": 1782765960000,
        "volume": 6.3888297
      },
      {
        "close": 60263.87,
        "close_time_ms": 1782766080000,
        "high": 60294.29,
        "low": 60260.29,
        "open": 60282.2,
        "open_time_ms": 1782766020000,
        "volume": 5.31840494
      },
      {
        "close": 60296.5,
        "close_time_ms": 1782766140000,
        "high": 60296.51,
        "low": 60255.71,
        "open": 60263.87,
        "open_time_ms": 1782766080000,
        "volume": 2.53588694
      },
      {
        "close": 60308.34,
        "close_time_ms": 1782766200000,
        "high": 60311.05,
        "low": 60291.87,
        "open": 60296.5,
        "open_time_ms": 1782766140000,
        "volume": 1.76754818
      },
      {
        "close": 60261.1,
        "close_time_ms": 1782766260000,
        "high": 60308.34,
        "low": 60255.04,
        "open": 60308.33,
        "open_time_ms": 1782766200000,
        "volume": 11.40278546
      },
      {
        "close": 60226.77,
        "close_time_ms": 1782766320000,
        "high": 60268.02,
        "low": 60221.99,
        "open": 60262.84,
        "open_time_ms": 1782766260000,
        "volume": 6.77095134
      },
      {
        "close": 60228.01,
        "close_time_ms": 1782766380000,
        "high": 60249.0,
        "low": 60221.82,
        "open": 60226.78,
        "open_time_ms": 1782766320000,
        "volume": 6.19565563
      },
      {
        "close": 60218.24,
        "close_time_ms": 1782766440000,
        "high": 60228.01,
        "low": 60208.01,
        "open": 60228.01,
        "open_time_ms": 1782766380000,
        "volume": 3.30933064
      },
      {
        "close": 60211.78,
        "close_time_ms": 1782766500000,
        "high": 60225.65,
        "low": 60211.78,
        "open": 60218.24,
        "open_time_ms": 1782766440000,
        "volume": 2.55561755
      },
      {
        "close": 60211.49,
        "close_time_ms": 1782766560000,
        "high": 60215.42,
        "low": 60205.0,
        "open": 60211.79,
        "open_time_ms": 1782766500000,
        "volume": 2.79753769
      },
      {
        "close": 60209.83,
        "close_time_ms": 1782766620000,
        "high": 60227.86,
        "low": 60205.0,
        "open": 60211.48,
        "open_time_ms": 1782766560000,
        "volume": 3.30004956
      },
      {
        "close": 60203.35,
        "close_time_ms": 1782766680000,
        "high": 60217.52,
        "low": 60188.15,
        "open": 60209.82,
        "open_time_ms": 1782766620000,
        "volume": 6.52219023
      },
      {
        "close": 60205.99,
        "close_time_ms": 1782766740000,
        "high": 60216.25,
        "low": 60196.84,
        "open": 60203.35,
        "open_time_ms": 1782766680000,
        "volume": 5.78930099
      },
      {
        "close": 60197.71,
        "close_time_ms": 1782766800000,
        "high": 60206.0,
        "low": 60197.68,
        "open": 60205.99,
        "open_time_ms": 1782766740000,
        "volume": 1.53432424
      },
      {
        "close": 60210.95,
        "close_time_ms": 1782766860000,
        "high": 60215.17,
        "low": 60203.19,
        "open": 60203.19,
        "open_time_ms": 1782766800000,
        "volume": 2.57205796
      },
      {
        "close": 60228.28,
        "close_time_ms": 1782766920000,
        "high": 60234.0,
        "low": 60205.98,
        "open": 60210.94,
        "open_time_ms": 1782766860000,
        "volume": 2.29723851
      },
      {
        "close": 60225.98,
        "close_time_ms": 1782766980000,
        "high": 60232.31,
        "low": 60215.01,
        "open": 60228.28,
        "open_time_ms": 1782766920000,
        "volume": 7.97811053
      },
      {
        "close": 60217.06,
        "close_time_ms": 1782767040000,
        "high": 60267.12,
        "low": 60212.17,
        "open": 60225.99,
        "open_time_ms": 1782766980000,
        "volume": 11.18196437
      },
      {
        "close": 60197.41,
        "close_time_ms": 1782767100000,
        "high": 60221.56,
        "low": 60167.66,
        "open": 60217.07,
        "open_time_ms": 1782767040000,
        "volume": 11.21687167
      },
      {
        "close": 60177.92,
        "close_time_ms": 1782767160000,
        "high": 60205.9,
        "low": 60160.86,
        "open": 60197.41,
        "open_time_ms": 1782767100000,
        "volume": 19.90225943
      },
      {
        "close": 60205.0,
        "close_time_ms": 1782767220000,
        "high": 60206.72,
        "low": 60177.93,
        "open": 60177.93,
        "open_time_ms": 1782767160000,
        "volume": 3.15185052
      },
      {
        "close": 60240.0,
        "close_time_ms": 1782767280000,
        "high": 60240.0,
        "low": 60204.99,
        "open": 60204.99,
        "open_time_ms": 1782767220000,
        "volume": 6.87326129
      },
      {
        "close": 60239.94,
        "close_time_ms": 1782767340000,
        "high": 60260.86,
        "low": 60231.64,
        "open": 60240.0,
        "open_time_ms": 1782767280000,
        "volume": 8.23943168
      },
      {
        "close": 60223.93,
        "close_time_ms": 1782767400000,
        "high": 60248.18,
        "low": 60219.86,
        "open": 60239.95,
        "open_time_ms": 1782767340000,
        "volume": 3.70527165
      },
      {
        "close": 60235.99,
        "close_time_ms": 1782767460000,
        "high": 60237.63,
        "low": 60223.29,
        "open": 60223.94,
        "open_time_ms": 1782767400000,
        "volume": 5.35718542
      },
      {
        "close": 60255.05,
        "close_time_ms": 1782767520000,
        "high": 60264.1,
        "low": 60235.99,
        "open": 60235.99,
        "open_time_ms": 1782767460000,
        "volume": 2.69038712
      },
      {
        "close": 60259.71,
        "close_time_ms": 1782767580000,
        "high": 60266.68,
        "low": 60255.05,
        "open": 60255.06,
        "open_time_ms": 1782767520000,
        "volume": 2.1250222
      },
      {
        "close": 60305.81,
        "close_time_ms": 1782767640000,
        "high": 60323.56,
        "low": 60259.71,
        "open": 60259.71,
        "open_time_ms": 1782767580000,
        "volume": 5.07374789
      },
      {
        "close": 60317.75,
        "close_time_ms": 1782767700000,
        "high": 60323.81,
        "low": 60304.53,
        "open": 60305.82,
        "open_time_ms": 1782767640000,
        "volume": 2.27373879
      },
      {
        "close": 60290.18,
        "close_time_ms": 1782767760000,
        "high": 60320.41,
        "low": 60288.26,
        "open": 60317.75,
        "open_time_ms": 1782767700000,
        "volume": 4.24074439
      },
      {
        "close": 60268.93,
        "close_time_ms": 1782767820000,
        "high": 60300.33,
        "low": 60262.11,
        "open": 60290.17,
        "open_time_ms": 1782767760000,
        "volume": 3.5741104
      },
      {
        "close": 60250.0,
        "close_time_ms": 1782767880000,
        "high": 60268.94,
        "low": 60245.98,
        "open": 60268.93,
        "open_time_ms": 1782767820000,
        "volume": 4.40371811
      },
      {
        "close": 60240.95,
        "close_time_ms": 1782767940000,
        "high": 60256.39,
        "low": 60233.9,
        "open": 60249.75,
        "open_time_ms": 1782767880000,
        "volume": 4.63077437
      },
      {
        "close": 60227.5,
        "close_time_ms": 1782768000000,
        "high": 60250.0,
        "low": 60223.02,
        "open": 60240.95,
        "open_time_ms": 1782767940000,
        "volume": 2.64898694
      },
      {
        "close": 60248.99,
        "close_time_ms": 1782768060000,
        "high": 60249.0,
        "low": 60223.32,
        "open": 60227.51,
        "open_time_ms": 1782768000000,
        "volume": 4.55937268
      },
      {
        "close": 60239.94,
        "close_time_ms": 1782768120000,
        "high": 60249.0,
        "low": 60215.58,
        "open": 60248.99,
        "open_time_ms": 1782768060000,
        "volume": 4.61285616
      },
      {
        "close": 60252.02,
        "close_time_ms": 1782768180000,
        "high": 60252.02,
        "low": 60230.23,
        "open": 60239.93,
        "open_time_ms": 1782768120000,
        "volume": 3.13173553
      },
      {
        "close": 60233.23,
        "close_time_ms": 1782768240000,
        "high": 60252.02,
        "low": 60231.28,
        "open": 60252.02,
        "open_time_ms": 1782768180000,
        "volume": 2.07808948
      },
      {
        "close": 60209.99,
        "close_time_ms": 1782768300000,
        "high": 60233.28,
        "low": 60209.18,
        "open": 60233.23,
        "open_time_ms": 1782768240000,
        "volume": 2.35640455
      },
      {
        "close": 60217.95,
        "close_time_ms": 1782768360000,
        "high": 60224.0,
        "low": 60209.98,
        "open": 60209.99,
        "open_time_ms": 1782768300000,
        "volume": 2.11555464
      },
      {
        "close": 60211.61,
        "close_time_ms": 1782768420000,
        "high": 60223.24,
        "low": 60209.29,
        "open": 60217.95,
        "open_time_ms": 1782768360000,
        "volume": 2.11638024
      },
      {
        "close": 60223.97,
        "close_time_ms": 1782768480000,
        "high": 60223.98,
        "low": 60211.61,
        "open": 60211.61,
        "open_time_ms": 1782768420000,
        "volume": 1.46481596
      },
      {
        "close": 60220.95,
        "close_time_ms": 1782768540000,
        "high": 60223.97,
        "low": 60213.28,
        "open": 60223.97,
        "open_time_ms": 1782768480000,
        "volume": 1.75375057
      },
      {
        "close": 60257.43,
        "close_time_ms": 1782768600000,
        "high": 60261.08,
        "low": 60220.95,
        "open": 60220.95,
        "open_time_ms": 1782768540000,
        "volume": 2.4829064
      },
      {
        "close": 60291.53,
        "close_time_ms": 1782768660000,
        "high": 60300.0,
        "low": 60257.43,
        "open": 60257.43,
        "open_time_ms": 1782768600000,
        "volume": 5.78446995
      },
      {
        "close": 60296.4,
        "close_time_ms": 1782768720000,
        "high": 60297.3,
        "low": 60281.32,
        "open": 60291.53,
        "open_time_ms": 1782768660000,
        "volume": 2.07348415
      },
      {
        "close": 60298.25,
        "close_time_ms": 1782768780000,
        "high": 60309.29,
        "low": 60296.39,
        "open": 60296.39,
        "open_time_ms": 1782768720000,
        "volume": 2.32912392
      },
      {
        "close": 60329.39,
        "close_time_ms": 1782768840000,
        "high": 60332.03,
        "low": 60298.25,
        "open": 60298.25,
        "open_time_ms": 1782768780000,
        "volume": 3.51811352
      },
      {
        "close": 60314.87,
        "close_time_ms": 1782768900000,
        "high": 60330.18,
        "low": 60306.82,
        "open": 60329.41,
        "open_time_ms": 1782768840000,
        "volume": 4.4291326
      },
      {
        "close": 60314.64,
        "close_time_ms": 1782768960000,
        "high": 60325.34,
        "low": 60310.08,
        "open": 60314.88,
        "open_time_ms": 1782768900000,
        "volume": 3.03959608
      },
      {
        "close": 60337.3,
        "close_time_ms": 1782769020000,
        "high": 60346.23,
        "low": 60313.6,
        "open": 60313.61,
        "open_time_ms": 1782768960000,
        "volume": 5.82480117
      },
      {
        "close": 60321.48,
        "close_time_ms": 1782769080000,
        "high": 60336.93,
        "low": 60300.34,
        "open": 60336.92,
        "open_time_ms": 1782769020000,
        "volume": 3.71381337
      },
      {
        "close": 60347.41,
        "close_time_ms": 1782769140000,
        "high": 60347.42,
        "low": 60321.49,
        "open": 60321.49,
        "open_time_ms": 1782769080000,
        "volume": 2.92696452
      },
      {
        "close": 60374.77,
        "close_time_ms": 1782769200000,
        "high": 60374.77,
        "low": 60347.4,
        "open": 60347.42,
        "open_time_ms": 1782769140000,
        "volume": 3.04496776
      },
      {
        "close": 60383.61,
        "close_time_ms": 1782769260000,
        "high": 60398.35,
        "low": 60355.73,
        "open": 60374.76,
        "open_time_ms": 1782769200000,
        "volume": 7.46968345
      },
      {
        "close": 60393.25,
        "close_time_ms": 1782769320000,
        "high": 60398.26,
        "low": 60383.61,
        "open": 60383.61,
        "open_time_ms": 1782769260000,
        "volume": 2.74070568
      },
      {
        "close": 60362.37,
        "close_time_ms": 1782769380000,
        "high": 60393.95,
        "low": 60318.77,
        "open": 60393.25,
        "open_time_ms": 1782769320000,
        "volume": 28.60171782
      },
      {
        "close": 60360.75,
        "close_time_ms": 1782769440000,
        "high": 60384.9,
        "low": 60349.78,
        "open": 60362.38,
        "open_time_ms": 1782769380000,
        "volume": 2.45182958
      },
      {
        "close": 60376.77,
        "close_time_ms": 1782769500000,
        "high": 60381.88,
        "low": 60355.22,
        "open": 60360.74,
        "open_time_ms": 1782769440000,
        "volume": 4.43959981
      },
      {
        "close": 60389.8,
        "close_time_ms": 1782769560000,
        "high": 60390.93,
        "low": 60368.95,
        "open": 60374.71,
        "open_time_ms": 1782769500000,
        "volume": 2.2184316
      },
      {
        "close": 60382.17,
        "close_time_ms": 1782769620000,
        "high": 60393.8,
        "low": 60373.51,
        "open": 60389.79,
        "open_time_ms": 1782769560000,
        "volume": 1.51660432
      },
      {
        "close": 60414.97,
        "close_time_ms": 1782769680000,
        "high": 60414.99,
        "low": 60382.19,
        "open": 60382.19,
        "open_time_ms": 1782769620000,
        "volume": 13.31651141
      },
      {
        "close": 60421.15,
        "close_time_ms": 1782769740000,
        "high": 60428.44,
        "low": 60411.53,
        "open": 60414.97,
        "open_time_ms": 1782769680000,
        "volume": 2.51903936
      },
      {
        "close": 60412.53,
        "close_time_ms": 1782769800000,
        "high": 60421.95,
        "low": 60409.44,
        "open": 60421.16,
        "open_time_ms": 1782769740000,
        "volume": 1.35161349
      },
      {
        "close": 60396.59,
        "close_time_ms": 1782769860000,
        "high": 60412.54,
        "low": 60385.65,
        "open": 60412.53,
        "open_time_ms": 1782769800000,
        "volume": 3.36978029
      },
      {
        "close": 60418.82,
        "close_time_ms": 1782769920000,
        "high": 60430.2,
        "low": 60396.63,
        "open": 60397.41,
        "open_time_ms": 1782769860000,
        "volume": 5.5292744
      },
      {
        "close": 60421.28,
        "close_time_ms": 1782769980000,
        "high": 60423.78,
        "low": 60414.31,
        "open": 60418.82,
        "open_time_ms": 1782769920000,
        "volume": 2.00593502
      },
      {
        "close": 60448.39,
        "close_time_ms": 1782770040000,
        "high": 60449.0,
        "low": 60390.79,
        "open": 60421.28,
        "open_time_ms": 1782769980000,
        "volume": 5.23059904
      },
      {
        "close": 60469.84,
        "close_time_ms": 1782770100000,
        "high": 60493.62,
        "low": 60448.59,
        "open": 60448.87,
        "open_time_ms": 1782770040000,
        "volume": 4.30038362
      },
      {
        "close": 60433.22,
        "close_time_ms": 1782770160000,
        "high": 60469.88,
        "low": 60433.22,
        "open": 60469.47,
        "open_time_ms": 1782770100000,
        "volume": 5.00235869
      },
      {
        "close": 60433.33,
        "close_time_ms": 1782770220000,
        "high": 60438.11,
        "low": 60433.22,
        "open": 60433.22,
        "open_time_ms": 1782770160000,
        "volume": 2.69094321
      },
      {
        "close": 60385.73,
        "close_time_ms": 1782770280000,
        "high": 60435.53,
        "low": 60383.84,
        "open": 60433.33,
        "open_time_ms": 1782770220000,
        "volume": 4.32104796
      },
      {
        "close": 60395.98,
        "close_time_ms": 1782770340000,
        "high": 60403.47,
        "low": 60369.8,
        "open": 60385.74,
        "open_time_ms": 1782770280000,
        "volume": 5.27158253
      },
      {
        "close": 60390.92,
        "close_time_ms": 1782770400000,
        "high": 60395.99,
        "low": 60371.61,
        "open": 60395.11,
        "open_time_ms": 1782770340000,
        "volume": 2.82787773
      },
      {
        "close": 60381.95,
        "close_time_ms": 1782770460000,
        "high": 60403.02,
        "low": 60360.74,
        "open": 60390.92,
        "open_time_ms": 1782770400000,
        "volume": 1.67502569
      },
      {
        "close": 60373.99,
        "close_time_ms": 1782770520000,
        "high": 60381.96,
        "low": 60363.76,
        "open": 60381.96,
        "open_time_ms": 1782770460000,
        "volume": 0.91785619
      },
      {
        "close": 60383.37,
        "close_time_ms": 1782770580000,
        "high": 60385.0,
        "low": 60369.73,
        "open": 60373.99,
        "open_time_ms": 1782770520000,
        "volume": 3.22505598
      },
      {
        "close": 60357.72,
        "close_time_ms": 1782770640000,
        "high": 60406.43,
        "low": 60354.76,
        "open": 60383.37,
        "open_time_ms": 1782770580000,
        "volume": 5.92842492
      },
      {
        "close": 60371.27,
        "close_time_ms": 1782770700000,
        "high": 60403.43,
        "low": 60357.72,
        "open": 60357.73,
        "open_time_ms": 1782770640000,
        "volume": 2.96103284
      },
      {
        "close": 60389.11,
        "close_time_ms": 1782770760000,
        "high": 60400.06,
        "low": 60355.56,
        "open": 60371.28,
        "open_time_ms": 1782770700000,
        "volume": 3.48244992
      },
      {
        "close": 60345.01,
        "close_time_ms": 1782770820000,
        "high": 60389.11,
        "low": 60339.6,
        "open": 60389.11,
        "open_time_ms": 1782770760000,
        "volume": 1.89153021
      },
      {
        "close": 60318.47,
        "close_time_ms": 1782770880000,
        "high": 60360.0,
        "low": 60318.46,
        "open": 60345.02,
        "open_time_ms": 1782770820000,
        "volume": 4.4714453
      },
      {
        "close": 60329.98,
        "close_time_ms": 1782770940000,
        "high": 60335.3,
        "low": 60301.51,
        "open": 60318.47,
        "open_time_ms": 1782770880000,
        "volume": 8.52433752
      },
      {
        "close": 60352.01,
        "close_time_ms": 1782771000000,
        "high": 60355.09,
        "low": 60328.65,
        "open": 60329.99,
        "open_time_ms": 1782770940000,
        "volume": 4.12910377
      },
      {
        "close": 60339.97,
        "close_time_ms": 1782771060000,
        "high": 60353.2,
        "low": 60338.06,
        "open": 60352.01,
        "open_time_ms": 1782771000000,
        "volume": 1.5891907
      },
      {
        "close": 60291.28,
        "close_time_ms": 1782771120000,
        "high": 60339.97,
        "low": 60271.25,
        "open": 60339.96,
        "open_time_ms": 1782771060000,
        "volume": 8.82906122
      },
      {
        "close": 60317.99,
        "close_time_ms": 1782771180000,
        "high": 60318.0,
        "low": 60259.78,
        "open": 60291.28,
        "open_time_ms": 1782771120000,
        "volume": 2.37401645
      },
      {
        "close": 60355.23,
        "close_time_ms": 1782771240000,
        "high": 60355.23,
        "low": 60314.95,
        "open": 60317.99,
        "open_time_ms": 1782771180000,
        "volume": 3.10132919
      },
      {
        "close": 60363.32,
        "close_time_ms": 1782771300000,
        "high": 60363.34,
        "low": 60336.58,
        "open": 60355.23,
        "open_time_ms": 1782771240000,
        "volume": 1.05307354
      },
      {
        "close": 60390.0,
        "close_time_ms": 1782771360000,
        "high": 60392.72,
        "low": 60363.33,
        "open": 60363.33,
        "open_time_ms": 1782771300000,
        "volume": 1.92665416
      },
      {
        "close": 60371.69,
        "close_time_ms": 1782771420000,
        "high": 60392.71,
        "low": 60370.9,
        "open": 60389.99,
        "open_time_ms": 1782771360000,
        "volume": 1.37498839
      },
      {
        "close": 60367.99,
        "close_time_ms": 1782771480000,
        "high": 60378.92,
        "low": 60351.7,
        "open": 60371.7,
        "open_time_ms": 1782771420000,
        "volume": 3.50775926
      },
      {
        "close": 60357.72,
        "close_time_ms": 1782771540000,
        "high": 60372.84,
        "low": 60335.72,
        "open": 60367.99,
        "open_time_ms": 1782771480000,
        "volume": 6.64778877
      },
      {
        "close": 60398.34,
        "close_time_ms": 1782771600000,
        "high": 60398.35,
        "low": 60352.11,
        "open": 60357.73,
        "open_time_ms": 1782771540000,
        "volume": 4.20842891
      },
      {
        "close": 60422.93,
        "close_time_ms": 1782771660000,
        "high": 60427.99,
        "low": 60398.34,
        "open": 60398.34,
        "open_time_ms": 1782771600000,
        "volume": 3.09882596
      },
      {
        "close": 60406.04,
        "close_time_ms": 1782771720000,
        "high": 60422.94,
        "low": 60406.04,
        "open": 60422.93,
        "open_time_ms": 1782771660000,
        "volume": 1.06137687
      },
      {
        "close": 60374.0,
        "close_time_ms": 1782771780000,
        "high": 60412.08,
        "low": 60369.81,
        "open": 60406.04,
        "open_time_ms": 1782771720000,
        "volume": 2.3221386
      },
      {
        "close": 60355.81,
        "close_time_ms": 1782771840000,
        "high": 60374.0,
        "low": 60345.64,
        "open": 60373.99,
        "open_time_ms": 1782771780000,
        "volume": 1.49144192
      },
      {
        "close": 60351.36,
        "close_time_ms": 1782771900000,
        "high": 60359.41,
        "low": 60348.66,
        "open": 60355.81,
        "open_time_ms": 1782771840000,
        "volume": 1.50139654
      },
      {
        "close": 60336.76,
        "close_time_ms": 1782771960000,
        "high": 60359.4,
        "low": 60336.58,
        "open": 60351.36,
        "open_time_ms": 1782771900000,
        "volume": 2.33351678
      },
      {
        "close": 60360.76,
        "close_time_ms": 1782772020000,
        "high": 60375.05,
        "low": 60333.56,
        "open": 60336.77,
        "open_time_ms": 1782771960000,
        "volume": 2.2943174
      },
      {
        "close": 60368.98,
        "close_time_ms": 1782772080000,
        "high": 60369.95,
        "low": 60358.67,
        "open": 60360.75,
        "open_time_ms": 1782772020000,
        "volume": 0.63577613
      },
      {
        "close": 60357.94,
        "close_time_ms": 1782772140000,
        "high": 60369.93,
        "low": 60357.94,
        "open": 60368.98,
        "open_time_ms": 1782772080000,
        "volume": 1.2378215
      },
      {
        "close": 60350.57,
        "close_time_ms": 1782772200000,
        "high": 60361.82,
        "low": 60336.49,
        "open": 60357.94,
        "open_time_ms": 1782772140000,
        "volume": 4.25763092
      },
      {
        "close": 60365.35,
        "close_time_ms": 1782772260000,
        "high": 60371.95,
        "low": 60350.57,
        "open": 60350.58,
        "open_time_ms": 1782772200000,
        "volume": 2.80533129
      },
      {
        "close": 60332.17,
        "close_time_ms": 1782772320000,
        "high": 60365.35,
        "low": 60330.65,
        "open": 60365.34,
        "open_time_ms": 1782772260000,
        "volume": 1.76408471
      },
      {
        "close": 60342.61,
        "close_time_ms": 1782772380000,
        "high": 60348.61,
        "low": 60316.37,
        "open": 60332.16,
        "open_time_ms": 1782772320000,
        "volume": 2.42159777
      },
      {
        "close": 60311.99,
        "close_time_ms": 1782772440000,
        "high": 60342.62,
        "low": 60311.53,
        "open": 60342.61,
        "open_time_ms": 1782772380000,
        "volume": 1.52016562
      },
      {
        "close": 60301.04,
        "close_time_ms": 1782772500000,
        "high": 60315.36,
        "low": 60296.8,
        "open": 60311.99,
        "open_time_ms": 1782772440000,
        "volume": 3.73864235
      },
      {
        "close": 60258.79,
        "close_time_ms": 1782772560000,
        "high": 60305.99,
        "low": 60252.0,
        "open": 60301.05,
        "open_time_ms": 1782772500000,
        "volume": 6.30116159
      },
      {
        "close": 60268.89,
        "close_time_ms": 1782772620000,
        "high": 60273.15,
        "low": 60250.98,
        "open": 60258.79,
        "open_time_ms": 1782772560000,
        "volume": 1.26760161
      },
      {
        "close": 60275.33,
        "close_time_ms": 1782772680000,
        "high": 60278.67,
        "low": 60264.27,
        "open": 60268.88,
        "open_time_ms": 1782772620000,
        "volume": 1.45197706
      },
      {
        "close": 60286.9,
        "close_time_ms": 1782772740000,
        "high": 60294.0,
        "low": 60273.16,
        "open": 60275.33,
        "open_time_ms": 1782772680000,
        "volume": 1.83158056
      },
      {
        "close": 60267.5,
        "close_time_ms": 1782772800000,
        "high": 60288.89,
        "low": 60267.12,
        "open": 60286.91,
        "open_time_ms": 1782772740000,
        "volume": 1.95147101
      },
      {
        "close": 60269.06,
        "close_time_ms": 1782772860000,
        "high": 60273.18,
        "low": 60258.48,
        "open": 60267.5,
        "open_time_ms": 1782772800000,
        "volume": 2.10263945
      },
      {
        "close": 60267.4,
        "close_time_ms": 1782772920000,
        "high": 60277.83,
        "low": 60264.01,
        "open": 60269.06,
        "open_time_ms": 1782772860000,
        "volume": 2.11984875
      },
      {
        "close": 60292.98,
        "close_time_ms": 1782772980000,
        "high": 60296.71,
        "low": 60267.4,
        "open": 60267.4,
        "open_time_ms": 1782772920000,
        "volume": 1.89885778
      },
      {
        "close": 60300.52,
        "close_time_ms": 1782773040000,
        "high": 60306.38,
        "low": 60287.2,
        "open": 60292.98,
        "open_time_ms": 1782772980000,
        "volume": 2.4530396
      },
      {
        "close": 60299.42,
        "close_time_ms": 1782773100000,
        "high": 60300.53,
        "low": 60290.0,
        "open": 60300.53,
        "open_time_ms": 1782773040000,
        "volume": 0.71109948
      },
      {
        "close": 60288.27,
        "close_time_ms": 1782773160000,
        "high": 60306.38,
        "low": 60285.73,
        "open": 60299.99,
        "open_time_ms": 1782773100000,
        "volume": 1.02931623
      },
      {
        "close": 60303.35,
        "close_time_ms": 1782773220000,
        "high": 60303.36,
        "low": 60288.28,
        "open": 60288.28,
        "open_time_ms": 1782773160000,
        "volume": 1.0523447
      },
      {
        "close": 60312.61,
        "close_time_ms": 1782773280000,
        "high": 60312.62,
        "low": 60303.35,
        "open": 60303.35,
        "open_time_ms": 1782773220000,
        "volume": 0.36624851
      },
      {
        "close": 60301.41,
        "close_time_ms": 1782773340000,
        "high": 60312.62,
        "low": 60295.66,
        "open": 60312.61,
        "open_time_ms": 1782773280000,
        "volume": 1.57394599
      },
      {
        "close": 60324.48,
        "close_time_ms": 1782773400000,
        "high": 60330.54,
        "low": 60301.41,
        "open": 60301.41,
        "open_time_ms": 1782773340000,
        "volume": 1.97571505
      },
      {
        "close": 60307.39,
        "close_time_ms": 1782773460000,
        "high": 60326.85,
        "low": 60303.31,
        "open": 60324.48,
        "open_time_ms": 1782773400000,
        "volume": 1.79945791
      },
      {
        "close": 60285.24,
        "close_time_ms": 1782773520000,
        "high": 60307.4,
        "low": 60279.2,
        "open": 60307.39,
        "open_time_ms": 1782773460000,
        "volume": 2.54601553
      },
      {
        "close": 60294.29,
        "close_time_ms": 1782773580000,
        "high": 60294.3,
        "low": 60276.19,
        "open": 60285.25,
        "open_time_ms": 1782773520000,
        "volume": 1.75472545
      },
      {
        "close": 60295.99,
        "close_time_ms": 1782773640000,
        "high": 60297.2,
        "low": 60293.24,
        "open": 60294.29,
        "open_time_ms": 1782773580000,
        "volume": 1.64610471
      },
      {
        "close": 60336.78,
        "close_time_ms": 1782773700000,
        "high": 60340.77,
        "low": 60295.99,
        "open": 60296.0,
        "open_time_ms": 1782773640000,
        "volume": 1.06624685
      },
      {
        "close": 60307.99,
        "close_time_ms": 1782773760000,
        "high": 60336.78,
        "low": 60307.99,
        "open": 60336.77,
        "open_time_ms": 1782773700000,
        "volume": 0.99271713
      },
      {
        "close": 60324.49,
        "close_time_ms": 1782773820000,
        "high": 60324.5,
        "low": 60306.38,
        "open": 60307.99,
        "open_time_ms": 1782773760000,
        "volume": 1.36536547
      },
      {
        "close": 60258.65,
        "close_time_ms": 1782773880000,
        "high": 60324.49,
        "low": 60252.02,
        "open": 60324.49,
        "open_time_ms": 1782773820000,
        "volume": 9.33365717
      },
      {
        "close": 60267.82,
        "close_time_ms": 1782773940000,
        "high": 60267.83,
        "low": 60250.72,
        "open": 60258.66,
        "open_time_ms": 1782773880000,
        "volume": 2.11893474
      },
      {
        "close": 60261.96,
        "close_time_ms": 1782774000000,
        "high": 60267.83,
        "low": 60252.0,
        "open": 60267.82,
        "open_time_ms": 1782773940000,
        "volume": 1.49234919
      },
      {
        "close": 60270.64,
        "close_time_ms": 1782774060000,
        "high": 60284.0,
        "low": 60252.27,
        "open": 60261.97,
        "open_time_ms": 1782774000000,
        "volume": 2.96582798
      },
      {
        "close": 60282.35,
        "close_time_ms": 1782774120000,
        "high": 60282.72,
        "low": 60261.08,
        "open": 60270.64,
        "open_time_ms": 1782774060000,
        "volume": 1.30745431
      },
      {
        "close": 60282.56,
        "close_time_ms": 1782774180000,
        "high": 60290.49,
        "low": 60263.71,
        "open": 60282.35,
        "open_time_ms": 1782774120000,
        "volume": 1.92602548
      },
      {
        "close": 60285.23,
        "close_time_ms": 1782774240000,
        "high": 60285.24,
        "low": 60282.56,
        "open": 60282.57,
        "open_time_ms": 1782774180000,
        "volume": 0.46042986
      },
      {
        "close": 60264.8,
        "close_time_ms": 1782774300000,
        "high": 60285.24,
        "low": 60262.0,
        "open": 60285.24,
        "open_time_ms": 1782774240000,
        "volume": 3.01194182
      },
      {
        "close": 60259.56,
        "close_time_ms": 1782774360000,
        "high": 60264.78,
        "low": 60254.0,
        "open": 60262.0,
        "open_time_ms": 1782774300000,
        "volume": 1.04857046
      },
      {
        "close": 60253.49,
        "close_time_ms": 1782774420000,
        "high": 60259.57,
        "low": 60239.94,
        "open": 60259.57,
        "open_time_ms": 1782774360000,
        "volume": 2.16557523
      },
      {
        "close": 60252.02,
        "close_time_ms": 1782774480000,
        "high": 60263.42,
        "low": 60252.02,
        "open": 60253.49,
        "open_time_ms": 1782774420000,
        "volume": 1.61394636
      },
      {
        "close": 60264.59,
        "close_time_ms": 1782774540000,
        "high": 60266.53,
        "low": 60252.03,
        "open": 60252.03,
        "open_time_ms": 1782774480000,
        "volume": 0.84989038
      },
      {
        "close": 60261.46,
        "close_time_ms": 1782774600000,
        "high": 60264.59,
        "low": 60259.99,
        "open": 60264.59,
        "open_time_ms": 1782774540000,
        "volume": 0.53844229
      },
      {
        "close": 60242.96,
        "close_time_ms": 1782774660000,
        "high": 60261.46,
        "low": 60233.99,
        "open": 60261.45,
        "open_time_ms": 1782774600000,
        "volume": 1.59501822
      },
      {
        "close": 60261.08,
        "close_time_ms": 1782774720000,
        "high": 60261.08,
        "low": 60242.95,
        "open": 60242.95,
        "open_time_ms": 1782774660000,
        "volume": 1.60218178
      },
      {
        "close": 60263.01,
        "close_time_ms": 1782774780000,
        "high": 60263.73,
        "low": 60242.09,
        "open": 60261.07,
        "open_time_ms": 1782774720000,
        "volume": 1.18187726
      },
      {
        "close": 60251.23,
        "close_time_ms": 1782774840000,
        "high": 60275.0,
        "low": 60243.32,
        "open": 60263.02,
        "open_time_ms": 1782774780000,
        "volume": 2.19816514
      },
      {
        "close": 60250.7,
        "close_time_ms": 1782774900000,
        "high": 60251.24,
        "low": 60245.16,
        "open": 60251.23,
        "open_time_ms": 1782774840000,
        "volume": 0.38668913
      }
    ],
    "interval": "1m"
  },
  "error": null,
  "fetched_at": "2026-06-29T23:16:06Z",
  "kind": "candles_1m",
  "notes": [],
  "schema_version": "phase2-data-v1",
  "source": "coinbase",
  "status": "ok"
}
