{
  "attempts": [
    {
      "error": "GET https://api.binance.com/api/v3/klines?symbol=BTCUSDT&interval=1m&limit=200 failed: HTTP Error 451: ",
      "fetched_at": "2026-06-10T12:35:35Z",
      "kind": "candles_1m",
      "latency_ms": 330,
      "notes": [],
      "source": "binance",
      "status": "failed"
    },
    {
      "error": null,
      "fetched_at": "2026-06-10T12:35:35Z",
      "kind": "candles_1m",
      "latency_ms": 53,
      "notes": [],
      "source": "coinbase",
      "status": "ok"
    }
  ],
  "data": {
    "candles": [
      {
        "close": 61017.83,
        "close_time_ms": 1781082900000,
        "high": 61082.65,
        "low": 61010.01,
        "open": 61070.83,
        "open_time_ms": 1781082840000,
        "volume": 13.17767137
      },
      {
        "close": 61043.96,
        "close_time_ms": 1781082960000,
        "high": 61046.95,
        "low": 61013.85,
        "open": 61015.6,
        "open_time_ms": 1781082900000,
        "volume": 6.36302563
      },
      {
        "close": 61020.0,
        "close_time_ms": 1781083020000,
        "high": 61043.96,
        "low": 60999.0,
        "open": 61043.96,
        "open_time_ms": 1781082960000,
        "volume": 42.25970687
      },
      {
        "close": 61057.91,
        "close_time_ms": 1781083080000,
        "high": 61061.91,
        "low": 61011.96,
        "open": 61020.0,
        "open_time_ms": 1781083020000,
        "volume": 5.00685041
      },
      {
        "close": 61085.62,
        "close_time_ms": 1781083140000,
        "high": 61088.8,
        "low": 61049.66,
        "open": 61057.91,
        "open_time_ms": 1781083080000,
        "volume": 1.74817242
      },
      {
        "close": 60990.47,
        "close_time_ms": 1781083200000,
        "high": 61085.62,
        "low": 60964.85,
        "open": 61085.62,
        "open_time_ms": 1781083140000,
        "volume": 7.86551358
      },
      {
        "close": 60908.12,
        "close_time_ms": 1781083260000,
        "high": 60992.0,
        "low": 60861.41,
        "open": 60985.7,
        "open_time_ms": 1781083200000,
        "volume": 19.27241288
      },
      {
        "close": 60783.5,
        "close_time_ms": 1781083320000,
        "high": 60941.1,
        "low": 60708.92,
        "open": 60906.18,
        "open_time_ms": 1781083260000,
        "volume": 63.70554745
      },
      {
        "close": 60807.46,
        "close_time_ms": 1781083380000,
        "high": 60852.0,
        "low": 60770.13,
        "open": 60783.47,
        "open_time_ms": 1781083320000,
        "volume": 19.11070292
      },
      {
        "close": 60872.07,
        "close_time_ms": 1781083440000,
        "high": 60872.07,
        "low": 60803.37,
        "open": 60807.75,
        "open_time_ms": 1781083380000,
        "volume": 6.82747141
      },
      {
        "close": 60921.63,
        "close_time_ms": 1781083500000,
        "high": 60925.0,
        "low": 60876.19,
        "open": 60876.19,
        "open_time_ms": 1781083440000,
        "volume": 3.49515948
      },
      {
        "close": 61012.21,
        "close_time_ms": 1781083560000,
        "high": 61020.83,
        "low": 60897.23,
        "open": 60925.75,
        "open_time_ms": 1781083500000,
        "volume": 15.7512235
      },
      {
        "close": 61044.2,
        "close_time_ms": 1781083620000,
        "high": 61049.99,
        "low": 60991.84,
        "open": 61008.99,
        "open_time_ms": 1781083560000,
        "volume": 2.43980299
      },
      {
        "close": 61094.73,
        "close_time_ms": 1781083680000,
        "high": 61165.22,
        "low": 61045.39,
        "open": 61045.39,
        "open_time_ms": 1781083620000,
        "volume": 4.14560971
      },
      {
        "close": 61153.95,
        "close_time_ms": 1781083740000,
        "high": 61168.7,
        "low": 61090.97,
        "open": 61094.73,
        "open_time_ms": 1781083680000,
        "volume": 8.06182201
      },
      {
        "close": 61159.09,
        "close_time_ms": 1781083800000,
        "high": 61194.21,
        "low": 61136.4,
        "open": 61153.96,
        "open_time_ms": 1781083740000,
        "volume": 3.82694465
      },
      {
        "close": 61202.82,
        "close_time_ms": 1781083860000,
        "high": 61214.0,
        "low": 61134.04,
        "open": 61159.09,
        "open_time_ms": 1781083800000,
        "volume": 4.33576137
      },
      {
        "close": 61173.78,
        "close_time_ms": 1781083920000,
        "high": 61225.0,
        "low": 61161.24,
        "open": 61202.81,
        "open_time_ms": 1781083860000,
        "volume": 2.86610789
      },
      {
        "close": 61208.01,
        "close_time_ms": 1781083980000,
        "high": 61244.04,
        "low": 61165.3,
        "open": 61173.78,
        "open_time_ms": 1781083920000,
        "volume": 3.71719937
      },
      {
        "close": 61220.0,
        "close_time_ms": 1781084040000,
        "high": 61239.63,
        "low": 61207.31,
        "open": 61208.01,
        "open_time_ms": 1781083980000,
        "volume": 1.81200983
      },
      {
        "close": 61243.76,
        "close_time_ms": 1781084100000,
        "high": 61247.9,
        "low": 61216.0,
        "open": 61216.0,
        "open_time_ms": 1781084040000,
        "volume": 0.8370571
      },
      {
        "close": 61292.14,
        "close_time_ms": 1781084160000,
        "high": 61292.14,
        "low": 61236.0,
        "open": 61243.76,
        "open_time_ms": 1781084100000,
        "volume": 1.22222124
      },
      {
        "close": 61262.0,
        "close_time_ms": 1781084220000,
        "high": 61326.91,
        "low": 61256.16,
        "open": 61292.14,
        "open_time_ms": 1781084160000,
        "volume": 2.31849324
      },
      {
        "close": 61249.21,
        "close_time_ms": 1781084280000,
        "high": 61262.01,
        "low": 61211.55,
        "open": 61262.01,
        "open_time_ms": 1781084220000,
        "volume": 2.06213383
      },
      {
        "close": 61358.01,
        "close_time_ms": 1781084340000,
        "high": 61372.14,
        "low": 61249.21,
        "open": 61249.21,
        "open_time_ms": 1781084280000,
        "volume": 3.54059124
      },
      {
        "close": 61324.01,
        "close_time_ms": 1781084400000,
        "high": 61379.4,
        "low": 61324.01,
        "open": 61358.0,
        "open_time_ms": 1781084340000,
        "volume": 4.01485281
      },
      {
        "close": 61264.3,
        "close_time_ms": 1781084460000,
        "high": 61324.0,
        "low": 61236.96,
        "open": 61324.0,
        "open_time_ms": 1781084400000,
        "volume": 8.05706422
      },
      {
        "close": 61273.28,
        "close_time_ms": 1781084520000,
        "high": 61299.69,
        "low": 61264.3,
        "open": 61264.3,
        "open_time_ms": 1781084460000,
        "volume": 2.4333257
      },
      {
        "close": 61267.26,
        "close_time_ms": 1781084580000,
        "high": 61285.06,
        "low": 61264.42,
        "open": 61273.27,
        "open_time_ms": 1781084520000,
        "volume": 1.24878004
      },
      {
        "close": 61255.03,
        "close_time_ms": 1781084640000,
        "high": 61264.42,
        "low": 61223.12,
        "open": 61264.42,
        "open_time_ms": 1781084580000,
        "volume": 3.07296736
      },
      {
        "close": 61217.99,
        "close_time_ms": 1781084700000,
        "high": 61266.02,
        "low": 61202.26,
        "open": 61255.03,
        "open_time_ms": 1781084640000,
        "volume": 10.43219916
      },
      {
        "close": 61205.82,
        "close_time_ms": 1781084760000,
        "high": 61231.37,
        "low": 61185.01,
        "open": 61218.0,
        "open_time_ms": 1781084700000,
        "volume": 24.68348953
      },
      {
        "close": 61133.26,
        "close_time_ms": 1781084820000,
        "high": 61203.99,
        "low": 61129.8,
        "open": 61203.99,
        "open_time_ms": 1781084760000,
        "volume": 2.97472245
      },
      {
        "close": 61107.48,
        "close_time_ms": 1781084880000,
        "high": 61140.0,
        "low": 61101.73,
        "open": 61131.99,
        "open_time_ms": 1781084820000,
        "volume": 1.91887922
      },
      {
        "close": 61119.89,
        "close_time_ms": 1781084940000,
        "high": 61142.0,
        "low": 61105.8,
        "open": 61105.8,
        "open_time_ms": 1781084880000,
        "volume": 1.84099079
      },
      {
        "close": 61134.98,
        "close_time_ms": 1781085000000,
        "high": 61134.99,
        "low": 61103.99,
        "open": 61119.87,
        "open_time_ms": 1781084940000,
        "volume": 1.23047689
      },
      {
        "close": 61195.33,
        "close_time_ms": 1781085060000,
        "high": 61195.33,
        "low": 61119.87,
        "open": 61134.98,
        "open_time_ms": 1781085000000,
        "volume": 1.94688976
      },
      {
        "close": 61223.12,
        "close_time_ms": 1781085120000,
        "high": 61235.5,
        "low": 61181.82,
        "open": 61198.33,
        "open_time_ms": 1781085060000,
        "volume": 0.92711658
      },
      {
        "close": 61213.0,
        "close_time_ms": 1781085180000,
        "high": 61275.78,
        "low": 61213.0,
        "open": 61224.0,
        "open_time_ms": 1781085120000,
        "volume": 3.68727898
      },
      {
        "close": 61181.82,
        "close_time_ms": 1781085240000,
        "high": 61213.83,
        "low": 61181.82,
        "open": 61213.0,
        "open_time_ms": 1781085180000,
        "volume": 1.31369108
      },
      {
        "close": 61258.01,
        "close_time_ms": 1781085300000,
        "high": 61268.02,
        "low": 61181.83,
        "open": 61181.83,
        "open_time_ms": 1781085240000,
        "volume": 1.82048615
      },
      {
        "close": 61292.69,
        "close_time_ms": 1781085360000,
        "high": 61292.69,
        "low": 61250.73,
        "open": 61258.01,
        "open_time_ms": 1781085300000,
        "volume": 0.36348054
      },
      {
        "close": 61340.56,
        "close_time_ms": 1781085420000,
        "high": 61356.29,
        "low": 61292.69,
        "open": 61292.69,
        "open_time_ms": 1781085360000,
        "volume": 8.58598503
      },
      {
        "close": 61299.0,
        "close_time_ms": 1781085480000,
        "high": 61363.53,
        "low": 61299.0,
        "open": 61346.8,
        "open_time_ms": 1781085420000,
        "volume": 15.59158134
      },
      {
        "close": 61280.95,
        "close_time_ms": 1781085540000,
        "high": 61297.67,
        "low": 61273.71,
        "open": 61297.66,
        "open_time_ms": 1781085480000,
        "volume": 2.11268362
      },
      {
        "close": 61289.11,
        "close_time_ms": 1781085600000,
        "high": 61289.11,
        "low": 61273.7,
        "open": 61280.94,
        "open_time_ms": 1781085540000,
        "volume": 0.71497506
      },
      {
        "close": 61260.29,
        "close_time_ms": 1781085660000,
        "high": 61292.0,
        "low": 61243.77,
        "open": 61289.1,
        "open_time_ms": 1781085600000,
        "volume": 3.04156582
      },
      {
        "close": 61256.15,
        "close_time_ms": 1781085720000,
        "high": 61299.51,
        "low": 61238.21,
        "open": 61260.29,
        "open_time_ms": 1781085660000,
        "volume": 11.32598994
      },
      {
        "close": 61239.64,
        "close_time_ms": 1781085780000,
        "high": 61298.15,
        "low": 61239.64,
        "open": 61256.15,
        "open_time_ms": 1781085720000,
        "volume": 10.83480747
      },
      {
        "close": 61247.9,
        "close_time_ms": 1781085840000,
        "high": 61247.9,
        "low": 61206.6,
        "open": 61239.65,
        "open_time_ms": 1781085780000,
        "volume": 3.92697197
      },
      {
        "close": 61235.51,
        "close_time_ms": 1781085900000,
        "high": 61274.26,
        "low": 61226.69,
        "open": 61251.99,
        "open_time_ms": 1781085840000,
        "volume": 15.93705354
      },
      {
        "close": 61133.98,
        "close_time_ms": 1781085960000,
        "high": 61238.03,
        "low": 61113.3,
        "open": 61235.51,
        "open_time_ms": 1781085900000,
        "volume": 17.1055049
      },
      {
        "close": 61133.12,
        "close_time_ms": 1781086020000,
        "high": 61171.06,
        "low": 61133.12,
        "open": 61133.99,
        "open_time_ms": 1781085960000,
        "volume": 2.34945292
      },
      {
        "close": 61115.99,
        "close_time_ms": 1781086080000,
        "high": 61143.08,
        "low": 61115.99,
        "open": 61134.14,
        "open_time_ms": 1781086020000,
        "volume": 0.76185605
      },
      {
        "close": 61156.33,
        "close_time_ms": 1781086140000,
        "high": 61163.02,
        "low": 61115.99,
        "open": 61116.0,
        "open_time_ms": 1781086080000,
        "volume": 3.0427014
      },
      {
        "close": 61202.3,
        "close_time_ms": 1781086200000,
        "high": 61202.46,
        "low": 61156.33,
        "open": 61156.33,
        "open_time_ms": 1781086140000,
        "volume": 1.9703445
      },
      {
        "close": 61128.31,
        "close_time_ms": 1781086260000,
        "high": 61202.31,
        "low": 61111.61,
        "open": 61202.3,
        "open_time_ms": 1781086200000,
        "volume": 1.70804968
      },
      {
        "close": 61135.98,
        "close_time_ms": 1781086320000,
        "high": 61147.61,
        "low": 61115.74,
        "open": 61122.84,
        "open_time_ms": 1781086260000,
        "volume": 0.29861192
      },
      {
        "close": 61193.84,
        "close_time_ms": 1781086380000,
        "high": 61195.0,
        "low": 61132.6,
        "open": 61135.98,
        "open_time_ms": 1781086320000,
        "volume": 0.68819117
      },
      {
        "close": 61218.88,
        "close_time_ms": 1781086440000,
        "high": 61223.83,
        "low": 61174.63,
        "open": 61193.85,
        "open_time_ms": 1781086380000,
        "volume": 1.11528244
      },
      {
        "close": 61190.08,
        "close_time_ms": 1781086500000,
        "high": 61246.99,
        "low": 61190.08,
        "open": 61217.41,
        "open_time_ms": 1781086440000,
        "volume": 3.99202915
      },
      {
        "close": 61152.02,
        "close_time_ms": 1781086560000,
        "high": 61225.82,
        "low": 61152.0,
        "open": 61185.95,
        "open_time_ms": 1781086500000,
        "volume": 10.73062033
      },
      {
        "close": 61154.3,
        "close_time_ms": 1781086620000,
        "high": 61177.68,
        "low": 61143.61,
        "open": 61152.02,
        "open_time_ms": 1781086560000,
        "volume": 3.8189352
      },
      {
        "close": 61101.0,
        "close_time_ms": 1781086680000,
        "high": 61154.31,
        "low": 61097.03,
        "open": 61154.3,
        "open_time_ms": 1781086620000,
        "volume": 2.45939053
      },
      {
        "close": 61103.35,
        "close_time_ms": 1781086740000,
        "high": 61140.53,
        "low": 61100.74,
        "open": 61103.5,
        "open_time_ms": 1781086680000,
        "volume": 2.91655962
      },
      {
        "close": 61143.02,
        "close_time_ms": 1781086800000,
        "high": 61165.29,
        "low": 61103.35,
        "open": 61103.36,
        "open_time_ms": 1781086740000,
        "volume": 3.98559156
      },
      {
        "close": 61110.75,
        "close_time_ms": 1781086860000,
        "high": 61143.02,
        "low": 61107.48,
        "open": 61143.02,
        "open_time_ms": 1781086800000,
        "volume": 2.0152293
      },
      {
        "close": 61172.04,
        "close_time_ms": 1781086920000,
        "high": 61180.28,
        "low": 61107.48,
        "open": 61115.17,
        "open_time_ms": 1781086860000,
        "volume": 3.07108568
      },
      {
        "close": 61179.94,
        "close_time_ms": 1781086980000,
        "high": 61184.0,
        "low": 61161.17,
        "open": 61172.04,
        "open_time_ms": 1781086920000,
        "volume": 1.05563971
      },
      {
        "close": 61202.47,
        "close_time_ms": 1781087040000,
        "high": 61206.0,
        "low": 61162.42,
        "open": 61179.94,
        "open_time_ms": 1781086980000,
        "volume": 2.20555954
      },
      {
        "close": 61218.66,
        "close_time_ms": 1781087100000,
        "high": 61231.99,
        "low": 61194.97,
        "open": 61206.59,
        "open_time_ms": 1781087040000,
        "volume": 1.12057532
      },
      {
        "close": 61206.6,
        "close_time_ms": 1781087160000,
        "high": 61231.7,
        "low": 61204.67,
        "open": 61218.66,
        "open_time_ms": 1781087100000,
        "volume": 1.54793387
      },
      {
        "close": 61198.02,
        "close_time_ms": 1781087220000,
        "high": 61205.31,
        "low": 61169.46,
        "open": 61204.26,
        "open_time_ms": 1781087160000,
        "volume": 1.48460159
      },
      {
        "close": 61252.02,
        "close_time_ms": 1781087280000,
        "high": 61258.43,
        "low": 61200.0,
        "open": 61200.0,
        "open_time_ms": 1781087220000,
        "volume": 2.0526337
      },
      {
        "close": 61301.05,
        "close_time_ms": 1781087340000,
        "high": 61301.05,
        "low": 61243.77,
        "open": 61252.02,
        "open_time_ms": 1781087280000,
        "volume": 1.35782606
      },
      {
        "close": 61285.72,
        "close_time_ms": 1781087400000,
        "high": 61309.84,
        "low": 61276.81,
        "open": 61301.58,
        "open_time_ms": 1781087340000,
        "volume": 1.90007979
      },
      {
        "close": 61359.47,
        "close_time_ms": 1781087460000,
        "high": 61359.48,
        "low": 61268.55,
        "open": 61285.72,
        "open_time_ms": 1781087400000,
        "volume": 8.84696166
      },
      {
        "close": 61388.33,
        "close_time_ms": 1781087520000,
        "high": 61409.76,
        "low": 61331.99,
        "open": 61359.48,
        "open_time_ms": 1781087460000,
        "volume": 4.55356622
      },
      {
        "close": 61332.74,
        "close_time_ms": 1781087580000,
        "high": 61388.32,
        "low": 61326.37,
        "open": 61388.32,
        "open_time_ms": 1781087520000,
        "volume": 1.17899023
      },
      {
        "close": 61353.8,
        "close_time_ms": 1781087640000,
        "high": 61355.28,
        "low": 61309.99,
        "open": 61332.73,
        "open_time_ms": 1781087580000,
        "volume": 3.5801762
      },
      {
        "close": 61309.86,
        "close_time_ms": 1781087700000,
        "high": 61355.27,
        "low": 61309.85,
        "open": 61353.8,
        "open_time_ms": 1781087640000,
        "volume": 1.64061548
      },
      {
        "close": 61274.08,
        "close_time_ms": 1781087760000,
        "high": 61309.86,
        "low": 61264.42,
        "open": 61309.86,
        "open_time_ms": 1781087700000,
        "volume": 2.6246298
      },
      {
        "close": 61311.13,
        "close_time_ms": 1781087820000,
        "high": 61320.0,
        "low": 61276.81,
        "open": 61276.81,
        "open_time_ms": 1781087760000,
        "volume": 1.54790072
      },
      {
        "close": 61306.44,
        "close_time_ms": 1781087880000,
        "high": 61315.71,
        "low": 61289.2,
        "open": 61310.48,
        "open_time_ms": 1781087820000,
        "volume": 1.1722436
      },
      {
        "close": 61249.99,
        "close_time_ms": 1781087940000,
        "high": 61306.45,
        "low": 61239.64,
        "open": 61306.44,
        "open_time_ms": 1781087880000,
        "volume": 0.60767705
      },
      {
        "close": 61244.33,
        "close_time_ms": 1781088000000,
        "high": 61272.0,
        "low": 61238.43,
        "open": 61249.99,
        "open_time_ms": 1781087940000,
        "volume": 1.22802094
      },
      {
        "close": 61217.86,
        "close_time_ms": 1781088060000,
        "high": 61252.03,
        "low": 61213.27,
        "open": 61244.33,
        "open_time_ms": 1781088000000,
        "volume": 1.08600766
      },
      {
        "close": 61250.01,
        "close_time_ms": 1781088120000,
        "high": 61268.54,
        "low": 61213.26,
        "open": 61217.88,
        "open_time_ms": 1781088060000,
        "volume": 1.93319784
      },
      {
        "close": 61283.92,
        "close_time_ms": 1781088180000,
        "high": 61283.93,
        "low": 61247.9,
        "open": 61248.35,
        "open_time_ms": 1781088120000,
        "volume": 0.25853923
      },
      {
        "close": 61256.16,
        "close_time_ms": 1781088240000,
        "high": 61295.0,
        "low": 61256.16,
        "open": 61285.07,
        "open_time_ms": 1781088180000,
        "volume": 0.95849343
      },
      {
        "close": 61264.15,
        "close_time_ms": 1781088300000,
        "high": 61264.44,
        "low": 61250.0,
        "open": 61256.16,
        "open_time_ms": 1781088240000,
        "volume": 5.80448142
      },
      {
        "close": 61276.8,
        "close_time_ms": 1781088360000,
        "high": 61285.07,
        "low": 61260.29,
        "open": 61264.15,
        "open_time_ms": 1781088300000,
        "volume": 0.34846891
      },
      {
        "close": 61270.07,
        "close_time_ms": 1781088420000,
        "high": 61313.98,
        "low": 61264.42,
        "open": 61276.81,
        "open_time_ms": 1781088360000,
        "volume": 1.80528078
      },
      {
        "close": 61260.29,
        "close_time_ms": 1781088480000,
        "high": 61300.37,
        "low": 61260.29,
        "open": 61270.08,
        "open_time_ms": 1781088420000,
        "volume": 3.39398649
      },
      {
        "close": 61248.22,
        "close_time_ms": 1781088540000,
        "high": 61276.76,
        "low": 61235.01,
        "open": 61260.29,
        "open_time_ms": 1781088480000,
        "volume": 1.60753936
      },
      {
        "close": 61291.27,
        "close_time_ms": 1781088600000,
        "high": 61291.27,
        "low": 61244.89,
        "open": 61248.22,
        "open_time_ms": 1781088540000,
        "volume": 1.12940632
      },
      {
        "close": 61312.2,
        "close_time_ms": 1781088660000,
        "high": 61319.45,
        "low": 61285.29,
        "open": 61291.27,
        "open_time_ms": 1781088600000,
        "volume": 1.35356258
      },
      {
        "close": 61324.0,
        "close_time_ms": 1781088720000,
        "high": 61327.63,
        "low": 61301.82,
        "open": 61306.0,
        "open_time_ms": 1781088660000,
        "volume": 0.55606861
      },
      {
        "close": 61280.23,
        "close_time_ms": 1781088780000,
        "high": 61324.0,
        "low": 61280.0,
        "open": 61324.0,
        "open_time_ms": 1781088720000,
        "volume": 0.86736268
      },
      {
        "close": 61253.12,
        "close_time_ms": 1781088840000,
        "high": 61280.23,
        "low": 61231.38,
        "open": 61280.23,
        "open_time_ms": 1781088780000,
        "volume": 3.81801358
      },
      {
        "close": 61245.01,
        "close_time_ms": 1781088900000,
        "high": 61264.05,
        "low": 61242.8,
        "open": 61253.13,
        "open_time_ms": 1781088840000,
        "volume": 1.67687054
      },
      {
        "close": 61239.65,
        "close_time_ms": 1781088960000,
        "high": 61258.0,
        "low": 61239.64,
        "open": 61245.01,
        "open_time_ms": 1781088900000,
        "volume": 0.70435259
      },
      {
        "close": 61320.04,
        "close_time_ms": 1781089020000,
        "high": 61334.62,
        "low": 61231.48,
        "open": 61239.66,
        "open_time_ms": 1781088960000,
        "volume": 4.97065508
      },
      {
        "close": 61340.16,
        "close_time_ms": 1781089080000,
        "high": 61367.96,
        "low": 61289.2,
        "open": 61320.05,
        "open_time_ms": 1781089020000,
        "volume": 3.09085824
      },
      {
        "close": 61331.99,
        "close_time_ms": 1781089140000,
        "high": 61349.95,
        "low": 61325.78,
        "open": 61340.15,
        "open_time_ms": 1781089080000,
        "volume": 1.51676018
      },
      {
        "close": 61329.49,
        "close_time_ms": 1781089200000,
        "high": 61340.0,
        "low": 61325.8,
        "open": 61331.99,
        "open_time_ms": 1781089140000,
        "volume": 1.22918553
      },
      {
        "close": 61305.72,
        "close_time_ms": 1781089260000,
        "high": 61342.88,
        "low": 61305.72,
        "open": 61338.76,
        "open_time_ms": 1781089200000,
        "volume": 2.10568233
      },
      {
        "close": 61333.46,
        "close_time_ms": 1781089320000,
        "high": 61333.46,
        "low": 61289.75,
        "open": 61305.72,
        "open_time_ms": 1781089260000,
        "volume": 1.99364827
      },
      {
        "close": 61376.93,
        "close_time_ms": 1781089380000,
        "high": 61385.99,
        "low": 61331.39,
        "open": 61334.63,
        "open_time_ms": 1781089320000,
        "volume": 1.98463203
      },
      {
        "close": 61187.28,
        "close_time_ms": 1781089440000,
        "high": 61388.0,
        "low": 61125.0,
        "open": 61376.92,
        "open_time_ms": 1781089380000,
        "volume": 41.66766648
      },
      {
        "close": 60959.12,
        "close_time_ms": 1781089500000,
        "high": 61214.82,
        "low": 60920.0,
        "open": 61178.0,
        "open_time_ms": 1781089440000,
        "volume": 16.05524722
      },
      {
        "close": 61038.33,
        "close_time_ms": 1781089560000,
        "high": 61061.46,
        "low": 60905.0,
        "open": 60959.13,
        "open_time_ms": 1781089500000,
        "volume": 13.62007282
      },
      {
        "close": 60900.98,
        "close_time_ms": 1781089620000,
        "high": 61059.73,
        "low": 60799.82,
        "open": 61037.96,
        "open_time_ms": 1781089560000,
        "volume": 23.55126863
      },
      {
        "close": 61000.1,
        "close_time_ms": 1781089680000,
        "high": 61020.74,
        "low": 60886.25,
        "open": 60905.1,
        "open_time_ms": 1781089620000,
        "volume": 8.73325904
      },
      {
        "close": 61024.87,
        "close_time_ms": 1781089740000,
        "high": 61024.88,
        "low": 60968.0,
        "open": 61000.39,
        "open_time_ms": 1781089680000,
        "volume": 4.34516907
      },
      {
        "close": 61036.97,
        "close_time_ms": 1781089800000,
        "high": 61049.0,
        "low": 60964.27,
        "open": 61024.87,
        "open_time_ms": 1781089740000,
        "volume": 2.74311235
      },
      {
        "close": 61040.98,
        "close_time_ms": 1781089860000,
        "high": 61070.0,
        "low": 61012.5,
        "open": 61040.0,
        "open_time_ms": 1781089800000,
        "volume": 6.54218792
      },
      {
        "close": 61030.27,
        "close_time_ms": 1781089920000,
        "high": 61040.81,
        "low": 60938.4,
        "open": 61037.01,
        "open_time_ms": 1781089860000,
        "volume": 8.89093742
      },
      {
        "close": 60966.05,
        "close_time_ms": 1781089980000,
        "high": 61053.79,
        "low": 60955.99,
        "open": 61030.28,
        "open_time_ms": 1781089920000,
        "volume": 9.34346465
      },
      {
        "close": 60983.72,
        "close_time_ms": 1781090040000,
        "high": 61021.38,
        "low": 60953.82,
        "open": 60958.79,
        "open_time_ms": 1781089980000,
        "volume": 10.17014446
      },
      {
        "close": 61109.54,
        "close_time_ms": 1781090100000,
        "high": 61127.0,
        "low": 60967.81,
        "open": 60983.72,
        "open_time_ms": 1781090040000,
        "volume": 18.37769351
      },
      {
        "close": 61078.57,
        "close_time_ms": 1781090160000,
        "high": 61120.14,
        "low": 61057.42,
        "open": 61111.99,
        "open_time_ms": 1781090100000,
        "volume": 5.55734479
      },
      {
        "close": 61182.68,
        "close_time_ms": 1781090220000,
        "high": 61182.68,
        "low": 61095.81,
        "open": 61119.94,
        "open_time_ms": 1781090160000,
        "volume": 13.47989981
      },
      {
        "close": 61038.31,
        "close_time_ms": 1781090280000,
        "high": 61188.81,
        "low": 61038.3,
        "open": 61182.68,
        "open_time_ms": 1781090220000,
        "volume": 2.74207874
      },
      {
        "close": 61062.05,
        "close_time_ms": 1781090340000,
        "high": 61093.08,
        "low": 61029.01,
        "open": 61038.3,
        "open_time_ms": 1781090280000,
        "volume": 3.05586439
      },
      {
        "close": 60995.97,
        "close_time_ms": 1781090400000,
        "high": 61079.71,
        "low": 60980.47,
        "open": 61065.67,
        "open_time_ms": 1781090340000,
        "volume": 2.15482846
      },
      {
        "close": 61068.41,
        "close_time_ms": 1781090460000,
        "high": 61078.57,
        "low": 60995.96,
        "open": 60995.96,
        "open_time_ms": 1781090400000,
        "volume": 4.53717963
      },
      {
        "close": 61146.99,
        "close_time_ms": 1781090520000,
        "high": 61161.08,
        "low": 61068.42,
        "open": 61068.42,
        "open_time_ms": 1781090460000,
        "volume": 6.82800555
      },
      {
        "close": 61157.03,
        "close_time_ms": 1781090580000,
        "high": 61157.03,
        "low": 61126.0,
        "open": 61144.93,
        "open_time_ms": 1781090520000,
        "volume": 0.85753453
      },
      {
        "close": 61104.01,
        "close_time_ms": 1781090640000,
        "high": 61146.11,
        "low": 61104.01,
        "open": 61124.0,
        "open_time_ms": 1781090580000,
        "volume": 1.21185679
      },
      {
        "close": 61020.0,
        "close_time_ms": 1781090700000,
        "high": 61113.61,
        "low": 61012.49,
        "open": 61107.07,
        "open_time_ms": 1781090640000,
        "volume": 15.80688349
      },
      {
        "close": 60867.94,
        "close_time_ms": 1781090760000,
        "high": 61035.06,
        "low": 60825.9,
        "open": 61019.91,
        "open_time_ms": 1781090700000,
        "volume": 18.53884558
      },
      {
        "close": 60957.49,
        "close_time_ms": 1781090820000,
        "high": 60965.55,
        "low": 60869.97,
        "open": 60869.97,
        "open_time_ms": 1781090760000,
        "volume": 4.60505872
      },
      {
        "close": 60882.37,
        "close_time_ms": 1781090880000,
        "high": 60965.0,
        "low": 60859.68,
        "open": 60956.0,
        "open_time_ms": 1781090820000,
        "volume": 8.80873638
      },
      {
        "close": 60878.59,
        "close_time_ms": 1781090940000,
        "high": 60921.62,
        "low": 60876.2,
        "open": 60885.0,
        "open_time_ms": 1781090880000,
        "volume": 4.53533977
      },
      {
        "close": 60908.24,
        "close_time_ms": 1781091000000,
        "high": 60917.01,
        "low": 60858.0,
        "open": 60878.6,
        "open_time_ms": 1781090940000,
        "volume": 2.47648435
      },
      {
        "close": 60922.36,
        "close_time_ms": 1781091060000,
        "high": 60963.53,
        "low": 60908.23,
        "open": 60908.23,
        "open_time_ms": 1781091000000,
        "volume": 4.16677998
      },
      {
        "close": 60878.1,
        "close_time_ms": 1781091120000,
        "high": 60922.36,
        "low": 60860.98,
        "open": 60922.36,
        "open_time_ms": 1781091060000,
        "volume": 2.87068686
      },
      {
        "close": 60866.06,
        "close_time_ms": 1781091180000,
        "high": 60958.79,
        "low": 60860.62,
        "open": 60878.1,
        "open_time_ms": 1781091120000,
        "volume": 6.03468991
      },
      {
        "close": 60924.05,
        "close_time_ms": 1781091240000,
        "high": 60954.66,
        "low": 60866.07,
        "open": 60866.07,
        "open_time_ms": 1781091180000,
        "volume": 3.48836672
      },
      {
        "close": 60943.01,
        "close_time_ms": 1781091300000,
        "high": 60966.71,
        "low": 60900.98,
        "open": 60927.82,
        "open_time_ms": 1781091240000,
        "volume": 9.8478627
      },
      {
        "close": 60949.09,
        "close_time_ms": 1781091360000,
        "high": 60990.13,
        "low": 60917.51,
        "open": 60943.01,
        "open_time_ms": 1781091300000,
        "volume": 9.5382045
      },
      {
        "close": 60979.44,
        "close_time_ms": 1781091420000,
        "high": 60979.45,
        "low": 60938.14,
        "open": 60946.41,
        "open_time_ms": 1781091360000,
        "volume": 1.30383643
      },
      {
        "close": 60919.92,
        "close_time_ms": 1781091480000,
        "high": 60975.31,
        "low": 60902.4,
        "open": 60975.31,
        "open_time_ms": 1781091420000,
        "volume": 1.71128605
      },
      {
        "close": 60938.32,
        "close_time_ms": 1781091540000,
        "high": 60946.3,
        "low": 60902.62,
        "open": 60919.92,
        "open_time_ms": 1781091480000,
        "volume": 3.17896804
      },
      {
        "close": 60917.98,
        "close_time_ms": 1781091600000,
        "high": 60961.89,
        "low": 60917.97,
        "open": 60938.32,
        "open_time_ms": 1781091540000,
        "volume": 3.72311081
      },
      {
        "close": 60940.78,
        "close_time_ms": 1781091660000,
        "high": 60967.69,
        "low": 60917.5,
        "open": 60917.97,
        "open_time_ms": 1781091600000,
        "volume": 5.40016524
      },
      {
        "close": 60953.99,
        "close_time_ms": 1781091720000,
        "high": 60962.92,
        "low": 60896.85,
        "open": 60940.77,
        "open_time_ms": 1781091660000,
        "volume": 9.1833421
      },
      {
        "close": 60930.88,
        "close_time_ms": 1781091780000,
        "high": 60978.54,
        "low": 60930.88,
        "open": 60954.0,
        "open_time_ms": 1781091720000,
        "volume": 2.7990526
      },
      {
        "close": 60995.97,
        "close_time_ms": 1781091840000,
        "high": 61004.88,
        "low": 60914.99,
        "open": 60929.89,
        "open_time_ms": 1781091780000,
        "volume": 3.02519838
      },
      {
        "close": 60959.12,
        "close_time_ms": 1781091900000,
        "high": 61006.47,
        "low": 60956.77,
        "open": 60995.98,
        "open_time_ms": 1781091840000,
        "volume": 4.23846337
      },
      {
        "close": 60964.87,
        "close_time_ms": 1781091960000,
        "high": 60968.06,
        "low": 60914.87,
        "open": 60958.84,
        "open_time_ms": 1781091900000,
        "volume": 2.07010641
      },
      {
        "close": 61003.15,
        "close_time_ms": 1781092020000,
        "high": 61012.75,
        "low": 60958.8,
        "open": 60964.88,
        "open_time_ms": 1781091960000,
        "volume": 4.16664593
      },
      {
        "close": 61037.0,
        "close_time_ms": 1781092080000,
        "high": 61048.75,
        "low": 61004.23,
        "open": 61006.67,
        "open_time_ms": 1781092020000,
        "volume": 3.02042041
      },
      {
        "close": 60995.96,
        "close_time_ms": 1781092140000,
        "high": 61053.78,
        "low": 60981.24,
        "open": 61036.99,
        "open_time_ms": 1781092080000,
        "volume": 5.14463198
      },
      {
        "close": 60955.96,
        "close_time_ms": 1781092200000,
        "high": 61004.23,
        "low": 60946.43,
        "open": 60995.96,
        "open_time_ms": 1781092140000,
        "volume": 3.38163697
      },
      {
        "close": 60967.06,
        "close_time_ms": 1781092260000,
        "high": 60995.01,
        "low": 60958.79,
        "open": 60958.79,
        "open_time_ms": 1781092200000,
        "volume": 2.74360046
      },
      {
        "close": 61037.27,
        "close_time_ms": 1781092320000,
        "high": 61052.66,
        "low": 60967.06,
        "open": 60969.07,
        "open_time_ms": 1781092260000,
        "volume": 1.91695261
      },
      {
        "close": 61044.03,
        "close_time_ms": 1781092380000,
        "high": 61046.72,
        "low": 61020.75,
        "open": 61037.27,
        "open_time_ms": 1781092320000,
        "volume": 0.94767988
      },
      {
        "close": 60975.78,
        "close_time_ms": 1781092440000,
        "high": 61056.64,
        "low": 60975.32,
        "open": 61044.02,
        "open_time_ms": 1781092380000,
        "volume": 6.46970561
      },
      {
        "close": 60985.56,
        "close_time_ms": 1781092500000,
        "high": 61003.99,
        "low": 60976.01,
        "open": 60976.01,
        "open_time_ms": 1781092440000,
        "volume": 0.90838366
      },
      {
        "close": 61004.24,
        "close_time_ms": 1781092560000,
        "high": 61032.0,
        "low": 60991.79,
        "open": 60991.79,
        "open_time_ms": 1781092500000,
        "volume": 1.59758223
      },
      {
        "close": 60958.81,
        "close_time_ms": 1781092620000,
        "high": 61004.25,
        "low": 60952.69,
        "open": 61004.25,
        "open_time_ms": 1781092560000,
        "volume": 1.6673661
      },
      {
        "close": 60983.58,
        "close_time_ms": 1781092680000,
        "high": 61009.19,
        "low": 60958.8,
        "open": 60958.8,
        "open_time_ms": 1781092620000,
        "volume": 4.35823114
      },
      {
        "close": 60985.02,
        "close_time_ms": 1781092740000,
        "high": 61009.35,
        "low": 60983.57,
        "open": 60983.59,
        "open_time_ms": 1781092680000,
        "volume": 3.36374082
      },
      {
        "close": 60977.48,
        "close_time_ms": 1781092800000,
        "high": 60985.21,
        "low": 60969.61,
        "open": 60985.01,
        "open_time_ms": 1781092740000,
        "volume": 0.56957373
      },
      {
        "close": 60946.4,
        "close_time_ms": 1781092860000,
        "high": 60986.66,
        "low": 60920.0,
        "open": 60977.47,
        "open_time_ms": 1781092800000,
        "volume": 2.82079308
      },
      {
        "close": 60938.15,
        "close_time_ms": 1781092920000,
        "high": 60946.41,
        "low": 60900.9,
        "open": 60946.4,
        "open_time_ms": 1781092860000,
        "volume": 4.46096966
      },
      {
        "close": 60970.68,
        "close_time_ms": 1781092980000,
        "high": 60970.69,
        "low": 60906.11,
        "open": 60938.14,
        "open_time_ms": 1781092920000,
        "volume": 4.59480349
      },
      {
        "close": 60975.33,
        "close_time_ms": 1781093040000,
        "high": 61012.43,
        "low": 60970.69,
        "open": 60970.69,
        "open_time_ms": 1781092980000,
        "volume": 1.64924774
      },
      {
        "close": 61034.09,
        "close_time_ms": 1781093100000,
        "high": 61035.0,
        "low": 60968.73,
        "open": 60975.32,
        "open_time_ms": 1781093040000,
        "volume": 3.46303168
      },
      {
        "close": 61068.75,
        "close_time_ms": 1781093160000,
        "high": 61091.64,
        "low": 61034.09,
        "open": 61034.09,
        "open_time_ms": 1781093100000,
        "volume": 3.95607824
      },
      {
        "close": 61094.01,
        "close_time_ms": 1781093220000,
        "high": 61110.65,
        "low": 61070.3,
        "open": 61070.3,
        "open_time_ms": 1781093160000,
        "volume": 3.14438822
      },
      {
        "close": 61045.53,
        "close_time_ms": 1781093280000,
        "high": 61093.05,
        "low": 61033.21,
        "open": 61093.05,
        "open_time_ms": 1781093220000,
        "volume": 2.02084418
      },
      {
        "close": 61012.49,
        "close_time_ms": 1781093340000,
        "high": 61057.86,
        "low": 60992.89,
        "open": 61045.53,
        "open_time_ms": 1781093280000,
        "volume": 26.99398655
      },
      {
        "close": 61062.0,
        "close_time_ms": 1781093400000,
        "high": 61078.56,
        "low": 61012.49,
        "open": 61014.0,
        "open_time_ms": 1781093340000,
        "volume": 22.98216999
      },
      {
        "close": 61103.35,
        "close_time_ms": 1781093460000,
        "high": 61103.35,
        "low": 61059.0,
        "open": 61062.01,
        "open_time_ms": 1781093400000,
        "volume": 18.53067666
      },
      {
        "close": 61140.42,
        "close_time_ms": 1781093520000,
        "high": 61147.5,
        "low": 61102.57,
        "open": 61103.35,
        "open_time_ms": 1781093460000,
        "volume": 18.59356677
      },
      {
        "close": 61120.99,
        "close_time_ms": 1781093580000,
        "high": 61152.8,
        "low": 61103.35,
        "open": 61138.01,
        "open_time_ms": 1781093520000,
        "volume": 14.65719505
      },
      {
        "close": 61157.05,
        "close_time_ms": 1781093640000,
        "high": 61177.68,
        "low": 61089.0,
        "open": 61120.98,
        "open_time_ms": 1781093580000,
        "volume": 13.27570925
      },
      {
        "close": 61140.02,
        "close_time_ms": 1781093700000,
        "high": 61174.01,
        "low": 61116.01,
        "open": 61157.65,
        "open_time_ms": 1781093640000,
        "volume": 2.57685568
      },
      {
        "close": 61079.99,
        "close_time_ms": 1781093760000,
        "high": 61200.0,
        "low": 61062.05,
        "open": 61140.02,
        "open_time_ms": 1781093700000,
        "volume": 17.25165239
      },
      {
        "close": 61110.37,
        "close_time_ms": 1781093820000,
        "high": 61117.45,
        "low": 61079.25,
        "open": 61079.99,
        "open_time_ms": 1781093760000,
        "volume": 4.04515768
      },
      {
        "close": 61105.91,
        "close_time_ms": 1781093880000,
        "high": 61119.53,
        "low": 61066.16,
        "open": 61110.37,
        "open_time_ms": 1781093820000,
        "volume": 2.4256792
      },
      {
        "close": 61062.76,
        "close_time_ms": 1781093940000,
        "high": 61110.39,
        "low": 61038.3,
        "open": 61105.99,
        "open_time_ms": 1781093880000,
        "volume": 1.51639721
      },
      {
        "close": 61036.35,
        "close_time_ms": 1781094000000,
        "high": 61088.02,
        "low": 61009.21,
        "open": 61064.02,
        "open_time_ms": 1781093940000,
        "volume": 2.5832878
      },
      {
        "close": 61041.37,
        "close_time_ms": 1781094060000,
        "high": 61061.21,
        "low": 61020.75,
        "open": 61036.36,
        "open_time_ms": 1781094000000,
        "volume": 1.67547982
      },
      {
        "close": 61076.69,
        "close_time_ms": 1781094120000,
        "high": 61106.1,
        "low": 61041.37,
        "open": 61041.37,
        "open_time_ms": 1781094060000,
        "volume": 2.23330092
      },
      {
        "close": 61001.45,
        "close_time_ms": 1781094180000,
        "high": 61079.05,
        "low": 60995.17,
        "open": 61076.69,
        "open_time_ms": 1781094120000,
        "volume": 1.15171304
      },
      {
        "close": 61020.75,
        "close_time_ms": 1781094240000,
        "high": 61033.13,
        "low": 60995.14,
        "open": 61001.45,
        "open_time_ms": 1781094180000,
        "volume": 3.4053171
      },
      {
        "close": 61008.35,
        "close_time_ms": 1781094300000,
        "high": 61041.39,
        "low": 60994.36,
        "open": 61020.76,
        "open_time_ms": 1781094240000,
        "volume": 16.54019747
      },
      {
        "close": 61047.95,
        "close_time_ms": 1781094360000,
        "high": 61064.0,
        "low": 61008.35,
        "open": 61008.36,
        "open_time_ms": 1781094300000,
        "volume": 8.09516383
      },
      {
        "close": 61075.25,
        "close_time_ms": 1781094420000,
        "high": 61082.69,
        "low": 61037.98,
        "open": 61047.96,
        "open_time_ms": 1781094360000,
        "volume": 3.42222664
      },
      {
        "close": 61055.98,
        "close_time_ms": 1781094480000,
        "high": 61071.91,
        "low": 61041.0,
        "open": 61071.91,
        "open_time_ms": 1781094420000,
        "volume": 1.3731773
      },
      {
        "close": 61073.73,
        "close_time_ms": 1781094540000,
        "high": 61124.55,
        "low": 61057.91,
        "open": 61057.91,
        "open_time_ms": 1781094480000,
        "volume": 1.33560254
      },
      {
        "close": 61123.52,
        "close_time_ms": 1781094600000,
        "high": 61128.11,
        "low": 61066.0,
        "open": 61070.31,
        "open_time_ms": 1781094540000,
        "volume": 8.14363739
      },
      {
        "close": 61467.06,
        "close_time_ms": 1781094660000,
        "high": 61652.7,
        "low": 61090.12,
        "open": 61117.46,
        "open_time_ms": 1781094600000,
        "volume": 92.63242105
      },
      {
        "close": 61454.97,
        "close_time_ms": 1781094720000,
        "high": 61667.09,
        "low": 61406.67,
        "open": 61457.15,
        "open_time_ms": 1781094660000,
        "volume": 23.92626268
      },
      {
        "close": 61604.26,
        "close_time_ms": 1781094780000,
        "high": 61639.07,
        "low": 61404.85,
        "open": 61454.01,
        "open_time_ms": 1781094720000,
        "volume": 16.29560659
      },
      {
        "close": 61741.01,
        "close_time_ms": 1781094840000,
        "high": 61900.7,
        "low": 61598.95,
        "open": 61599.44,
        "open_time_ms": 1781094780000,
        "volume": 19.56575344
      }
    ],
    "interval": "1m"
  },
  "error": null,
  "fetched_at": "2026-06-10T12:35:35Z",
  "kind": "candles_1m",
  "notes": [],
  "schema_version": "phase2-data-v1",
  "source": "coinbase",
  "status": "ok"
}
